probs_runner/__init__.py
probs_runner/cli.py
probs_runner/datasource.py
probs_runner/endpoint.py
probs_runner/namespace.py
probs_runner/runners.py
probs_runner/utils.py
probs_runner-2.0.0.dist-info/LICENSE
probs_runner-2.0.0.dist-info/METADATA
probs_runner-2.0.0.dist-info/WHEEL
probs_runner-2.0.0.dist-info/entry_points.txt
probs_runner-2.0.0.dist-info/top_level.txt
probs_runner-2.0.0.dist-info/RECORD
