Metadata-Version: 2.1
Name: probs_runner
Version: 2.0.0
Summary: Tools to run the PRObs ontology scripts with RDFox
Home-page: https://github.com/ukfires/probs-runner
Author: Rick Lupton, Stefano Germano
Author-email: mail@ricklupton.name
Platform: any
License-File: LICENSE
Requires-Dist: rdfox-runner>=0.5.1
Requires-Dist: pandas
Requires-Dist: click>=8.0
Requires-Dist: importlib-resources; python_version <= "3.9"
Provides-Extra: docs
Requires-Dist: jupyter-book<0.16,>=0.15; extra == "docs"
Provides-Extra: test
Requires-Dist: pytest; extra == "test"
Requires-Dist: probs-module-endpoint==2.0.0a2; extra == "test"
Requires-Dist: probs-module-ontology==2.0.0a1; extra == "test"
Requires-Dist: probs-module-data-conversion==2.0.0a2; extra == "test"
Requires-Dist: probs-module-data-validation==2.0.0a1; extra == "test"
Requires-Dist: probs-module-kbc-hierarchy==2.0.0a2; extra == "test"
